[ {
  "id" : "cc9c4ec7-f9d5-478f-8c2a-2893944242ee",
  "title" : "Sample Event",
  "venue" : {
    "id" : "v1",
    "name" : "Main Hall",
    "capacity" : 100
  },
  "start" : 1759681537.821001000,
  "end" : 1759685137.821001000,
  "capacity" : 80
}, {
  "id" : "a5665300-6d17-454f-8273-cdc3118e07e5",
  "title" : "Sample Event",
  "venue" : {
    "id" : "v1",
    "name" : "Main Hall",
    "capacity" : 100
  },
  "start" : 1759694866.103733000,
  "end" : 1759698466.103733000,
  "capacity" : 80
}, {
  "id" : "b803d52c-8980-49ac-86a0-c6472c62b878",
  "title" : "Sample Event",
  "venue" : {
    "id" : "v1",
    "name" : "Main Hall",
    "capacity" : 100
  },
  "start" : 1759694866.785421000,
  "end" : 1759698466.785421000,
  "capacity" : 80
}, {
  "id" : "11377cf6-daf1-4f3f-9483-c254d84407f3",
  "title" : "Sample Event",
  "venue" : {
    "id" : "v1",
    "name" : "Main Hall",
    "capacity" : 100
  },
  "start" : 1759694867.042184000,
  "end" : 1759698467.042184000,
  "capacity" : 80
} ]